synochat/__init__.py
synochat/exceptions.py
synochat/webhooks.py
synochat-1.0.4.dist-info/LICENSE
synochat-1.0.4.dist-info/METADATA
synochat-1.0.4.dist-info/WHEEL
synochat-1.0.4.dist-info/top_level.txt
synochat-1.0.4.dist-info/RECORD
