Metadata-Version: 2.1
Name: synochat
Version: 1.0.4
Summary: A library for the Synology Chat API written in Python 3.
Home-page: https://github.com/bitcanon/synochat
Author: Mikael Schultz
Author-email: bitcanon@pm.me
Classifier: Programming Language :: Python :: 3
Classifier: License :: OSI Approved :: MIT License
Classifier: Operating System :: OS Independent
Requires-Python: >=3.6
License-File: LICENSE
Requires-Dist: requests
